threadop.py
threadop-0.1.1.dist-info/WHEEL
threadop-0.1.1.dist-info/METADATA
threadop-0.1.1.dist-info/RECORD
